django_nanoid_field-0.1.5.dist-info/licenses/LICENCE
nanoid_field/__init__.py
nanoid_field/fields.py
django_nanoid_field-0.1.5.dist-info/METADATA
django_nanoid_field-0.1.5.dist-info/WHEEL
django_nanoid_field-0.1.5.dist-info/top_level.txt
django_nanoid_field-0.1.5.dist-info/RECORD
