Metadata-Version: 2.4
Name: django-nanoid-field
Version: 0.1.5
Summary: Next generation NanoID in Django Model IDs
Author-email: Gokhan Ozturk <me@gokhan.tr>
License: MIT
Project-URL: Homepage, https://github.com/gwainor/django-nanoid-field
Project-URL: Documentation, https://github.com/gwainor/django-nanoid-field
Project-URL: Repository, https://github.com/gwainor/django-nanoid-field.git
Keywords: django,nanoid,django-field
Classifier: Development Status :: 4 - Beta
Classifier: Environment :: Web Environment
Classifier: Framework :: Django
Classifier: License :: OSI Approved :: MIT License
Classifier: Operating System :: OS Independent
Classifier: Programming Language :: Python
License-File: LICENCE
Requires-Dist: nanoid
Requires-Dist: django>=2
Dynamic: license-file
